{
    "version": "1.0.0.0",
    "statusCode": 200,
    "message": "Ok",
    "responseException": null,
    "result": [
        {
            "stationSerialNumber": "WMQISXM1V1-02088",
            "sunmccuTime": 1773819114545,
            "sunmccuDate": "2026-03-18T13:01:54Z",
            "location": "Shell_Thindigua_Nairobi_Kenya",
            "zone": "Nairobi_Kenya_Africa",
            "sunmccuRecordType": "STATION-HOURLY-MAINS-POWER-DATA",
            "sunmccuTxidKey": "1773819114-545865",
            "sunmccuData": "{\"Hourly Mains Power Status\": {\"0:00\": \"0\", \"1:00\": \"0\", \"2:00\": \"0\", \"3:00\": \"0\", \"4:00\": \"0\", \"5:00\": \"0\", \"6:00\": \"0\", \"7:00\": \"0\", \"8:00\": \"0\", \"9:00\": \"0\", \"10:00\": \"0\", \"11:00\": \"0\", \"12:00\": \"0\", \"13:00\": \"0\", \"14:00\": \"0\", \"15:00\": \"0\", \"16:00\": \"0\", \"17:00\": \"0\", \"18:00\": \"0\", \"19:00\": \"0\", \"20:00\": \"0\", \"21:00\": \"0\", \"22:00\": \"0\", \"23:00\": \"0\"}}",
            "sunmccuSource": "{\"type\": \"NAME\", \"address\": \"qis.xm.all.health\"}"
        },
        {
            "stationSerialNumber": "WMQISXM1V1-00915",
            "sunmccuTime": 1773819106626,
            "sunmccuDate": "2026-03-18T13:01:46Z",
            "location": "SSMKL_Mombasa_Road_Nairobi_Kenya",
            "zone": "Nairobi_Kenya_Africa",
            "sunmccuRecordType": "STATION-HOURLY-MAINS-POWER-DATA",
            "sunmccuTxidKey": "1773819106-626729",
            "sunmccuData": "{\"Hourly Mains Power Status\": {\"0:00\": \"0\", \"1:00\": \"0\", \"2:00\": \"0\", \"3:00\": \"0\", \"4:00\": \"0\", \"5:00\": \"0\", \"6:00\": \"0\", \"7:00\": \"0\", \"8:00\": \"0\", \"9:00\": \"0\", \"10:00\": \"0\", \"11:00\": \"0\", \"12:00\": \"0\", \"13:00\": \"0\", \"14:00\": \"0\", \"15:00\": \"0\", \"16:00\": \"0\", \"17:00\": \"0\", \"18:00\": \"0\", \"19:00\": \"0\", \"20:00\": \"0\", \"21:00\": \"0\", \"22:00\": \"0\", \"23:00\": \"0\"}}",
            "sunmccuSource": "{\"type\": \"NAME\", \"address\": \"qis.xm.all.health\"}"
        },
        {
            "stationSerialNumber": "WMQISXM1V1-00110",
            "sunmccuTime": 1773819105418,
            "sunmccuDate": "2026-03-18T13:01:45Z",
            "location": "AyalaTechnohub-Manila-Philippines",
            "zone": "Manila_Philippines",
            "sunmccuRecordType": "STATION-HOURLY-MAINS-POWER-DATA",
            "sunmccuTxidKey": "1773819105-418441",
            "sunmccuData": "{\"Hourly Mains Power Status\": {\"0:00\": \"0\", \"1:00\": \"0\", \"2:00\": \"0\", \"3:00\": \"0\", \"4:00\": \"0\", \"5:00\": \"0\", \"6:00\": \"0\", \"7:00\": \"0\", \"8:00\": \"0\", \"9:00\": \"0\", \"10:00\": \"0\", \"11:00\": \"0\", \"12:00\": \"0\", \"13:00\": \"0\", \"14:00\": \"0\", \"15:00\": \"0\", \"16:00\": \"0\", \"17:00\": \"0\", \"18:00\": \"0\", \"19:00\": \"0\", \"20:00\": \"0\", \"21:00\": \"0\", \"22:00\": \"0\", \"23:00\": \"0\"}}",
            "sunmccuSource": "{\"type\": \"NAME\", \"address\": \"qis.xm.all.health\"}"
        },
        {
            "stationSerialNumber": "WMQISXM1V1-02089",
            "sunmccuTime": 1773819104748,
            "sunmccuDate": "2026-03-18T13:01:44Z",
            "location": "Shell_GethinKaren_Nairobi_Kenya",
            "zone": "Nairobi_Kenya_Africa",
            "sunmccuRecordType": "STATION-HOURLY-MAINS-POWER-DATA",
            "sunmccuTxidKey": "1773819104-748522",
            "sunmccuData": "{\"Hourly Mains Power Status\": {\"0:00\": \"0\", \"1:00\": \"0\", \"2:00\": \"0\", \"3:00\": \"0\", \"4:00\": \"0\", \"5:00\": \"0\", \"6:00\": \"0\", \"7:00\": \"1\", \"8:00\": \"0\", \"9:00\": \"0\", \"10:00\": \"0\", \"11:00\": \"0\", \"12:00\": \"0\", \"13:00\": \"0\", \"14:00\": \"0\", \"15:00\": \"0\", \"16:00\": \"0\", \"17:00\": \"0\", \"18:00\": \"0\", \"19:00\": \"0\", \"20:00\": \"0\", \"21:00\": \"0\", \"22:00\": \"0\", \"23:00\": \"0\"}}",
            "sunmccuSource": "{\"type\": \"NAME\", \"address\": \"qis.xm.all.health\"}"
        },
        {
            "stationSerialNumber": "WMQISXM1V1-00913",
            "sunmccuTime": 1773819104180,
            "sunmccuDate": "2026-03-18T13:01:44Z",
            "location": "Shell_NorthView_ThikaRoad_Nairobi_Kenya",
            "zone": "Nairobi_Kenya_Africa",
            "sunmccuRecordType": "STATION-HOURLY-MAINS-POWER-DATA",
            "sunmccuTxidKey": "1773819104-180746",
            "sunmccuData": "{\"Hourly Mains Power Status\": {\"0:00\": \"0\", \"1:00\": \"0\", \"2:00\": \"0\", \"3:00\": \"0\", \"4:00\": \"0\", \"5:00\": \"0\", \"6:00\": \"0\", \"7:00\": \"0\", \"8:00\": \"0\", \"9:00\": \"0\", \"10:00\": \"0\", \"11:00\": \"0\", \"12:00\": \"0\", \"13:00\": \"0\", \"14:00\": \"0\", \"15:00\": \"0\", \"16:00\": \"0\", \"17:00\": \"0\", \"18:00\": \"0\", \"19:00\": \"0\", \"20:00\": \"0\", \"21:00\": \"0\", \"22:00\": \"0\", \"23:00\": \"0\"}}",
            "sunmccuSource": "{\"type\": \"NAME\", \"address\": \"qis.xm.all.health\"}"
        },
        {
            "stationSerialNumber": "WMQISXM1V1-00880",
            "sunmccuTime": 1773819101605,
            "sunmccuDate": "2026-03-18T13:01:41Z",
            "location": "SEAOIL_Mandaluyong _Manila_Philippines",
            "zone": "Manila_Philippines",
            "sunmccuRecordType": "STATION-HOURLY-MAINS-POWER-DATA",
            "sunmccuTxidKey": "1773819101-605002",
            "sunmccuData": "{\"Hourly Mains Power Status\": {\"0:00\": \"0\", \"1:00\": \"0\", \"2:00\": \"0\", \"3:00\": \"0\", \"4:00\": \"0\", \"5:00\": \"0\", \"6:00\": \"0\", \"7:00\": \"0\", \"8:00\": \"0\", \"9:00\": \"0\", \"10:00\": \"0\", \"11:00\": \"0\", \"12:00\": \"0\", \"13:00\": \"0\", \"14:00\": \"0\", \"15:00\": \"0\", \"16:00\": \"0\", \"17:00\": \"0\", \"18:00\": \"0\", \"19:00\": \"0\", \"20:00\": \"0\", \"21:00\": \"0\", \"22:00\": \"0\", \"23:00\": \"0\"}}",
            "sunmccuSource": "{\"type\": \"NAME\", \"address\": \"qis.xm.all.health\"}"
        },
        {
            "stationSerialNumber": "WMQISXM1V1-00881",
            "sunmccuTime": 1773819099840,
            "sunmccuDate": "2026-03-18T13:01:39Z",
            "location": "SEAOIL_Pasig_Manila_Philippines",
            "zone": "Manila_Philippines",
            "sunmccuRecordType": "STATION-HOURLY-MAINS-POWER-DATA",
            "sunmccuTxidKey": "1773819099-840874",
            "sunmccuData": "{\"Hourly Mains Power Status\": {\"0:00\": \"0\", \"1:00\": \"0\", \"2:00\": \"0\", \"3:00\": \"0\", \"4:00\": \"0\", \"5:00\": \"0\", \"6:00\": \"0\", \"7:00\": \"0\", \"8:00\": \"0\", \"9:00\": \"0\", \"10:00\": \"0\", \"11:00\": \"0\", \"12:00\": \"0\", \"13:00\": \"0\", \"14:00\": \"0\", \"15:00\": \"0\", \"16:00\": \"0\", \"17:00\": \"0\", \"18:00\": \"0\", \"19:00\": \"0\", \"20:00\": \"0\", \"21:00\": \"0\", \"22:00\": \"0\", \"23:00\": \"0\"}}",
            "sunmccuSource": "{\"type\": \"NAME\", \"address\": \"qis.xm.all.health\"}"
        },
        {
            "stationSerialNumber": "WMQISXM1V1-00911",
            "sunmccuTime": 1773819099834,
            "sunmccuDate": "2026-03-18T13:01:39Z",
            "location": "PVT_Dagoretti Road_Nairobi_Kenya",
            "zone": "Nairobi_Kenya_Africa",
            "sunmccuRecordType": "STATION-HOURLY-MAINS-POWER-DATA",
            "sunmccuTxidKey": "1773819099-834929",
            "sunmccuData": "{\"Hourly Mains Power Status\": {\"0:00\": \"0\", \"1:00\": \"0\", \"2:00\": \"0\", \"3:00\": \"0\", \"4:00\": \"0\", \"5:00\": \"0\", \"6:00\": \"0\", \"7:00\": \"0\", \"8:00\": \"0\", \"9:00\": \"0\", \"10:00\": \"0\", \"11:00\": \"0\", \"12:00\": \"0\", \"13:00\": \"0\", \"14:00\": \"0\", \"15:00\": \"0\", \"16:00\": \"0\", \"17:00\": \"0\", \"18:00\": \"0\", \"19:00\": \"0\", \"20:00\": \"0\", \"21:00\": \"0\", \"22:00\": \"0\", \"23:00\": \"0\"}}",
            "sunmccuSource": "{\"type\": \"NAME\", \"address\": \"qis.xm.all.health\"}"
        },
        {
            "stationSerialNumber": "WMQISXM1V1-02016",
            "sunmccuTime": 1773819096645,
            "sunmccuDate": "2026-03-18T13:01:36Z",
            "location": "SEAOIL_Guadalupe_Manila_Philippines",
            "zone": "Manila_Philippines",
            "sunmccuRecordType": "STATION-HOURLY-MAINS-POWER-DATA",
            "sunmccuTxidKey": "1773819096-645557",
            "sunmccuData": "{\"Hourly Mains Power Status\": {\"0:00\": \"0\", \"1:00\": \"0\", \"2:00\": \"0\", \"3:00\": \"0\", \"4:00\": \"0\", \"5:00\": \"0\", \"6:00\": \"0\", \"7:00\": \"0\", \"8:00\": \"0\", \"9:00\": \"0\", \"10:00\": \"0\", \"11:00\": \"0\", \"12:00\": \"0\", \"13:00\": \"0\", \"14:00\": \"0\", \"15:00\": \"0\", \"16:00\": \"0\", \"17:00\": \"0\", \"18:00\": \"0\", \"19:00\": \"0\", \"20:00\": \"0\", \"21:00\": \"0\", \"22:00\": \"0\", \"23:00\": \"0\"}}",
            "sunmccuSource": "{\"type\": \"NAME\", \"address\": \"qis.xm.all.health\"}"
        },
        {
            "stationSerialNumber": "WMQISXM1V1-00912",
            "sunmccuTime": 1773819021490,
            "sunmccuDate": "2026-03-18T13:00:21Z",
            "location": "Shell_Riruta.Kawangware_Nairobi_Kenya",
            "zone": "Nairobi_Kenya_Africa",
            "sunmccuRecordType": "STATION-HOURLY-MAINS-POWER-DATA",
            "sunmccuTxidKey": "1773819021-490959",
            "sunmccuData": "{\"Hourly Mains Power Status\": {\"0:00\": \"0\", \"1:00\": \"0\", \"2:00\": \"0\", \"3:00\": \"0\", \"4:00\": \"0\", \"5:00\": \"0\", \"6:00\": \"0\", \"7:00\": \"0\", \"8:00\": \"0\", \"9:00\": \"0\", \"10:00\": \"0\", \"11:00\": \"0\", \"12:00\": \"0\", \"13:00\": \"0\", \"14:00\": \"0\", \"15:00\": \"0\", \"16:00\": \"0\", \"17:00\": \"0\", \"18:00\": \"0\", \"19:00\": \"0\", \"20:00\": \"0\", \"21:00\": \"0\", \"22:00\": \"0\", \"23:00\": \"0\"}}",
            "sunmccuSource": "{\"type\": \"NAME\", \"address\": \"qis.xm.all.health\"}"
        },
        {
            "stationSerialNumber": "WMQISXM1V1-00153",
            "sunmccuTime": 1773819000122,
            "sunmccuDate": "2026-03-18T13:00:00Z",
            "location": "SSMKL_Mombasa_Road_Nairobi_Kenya",
            "zone": "Nairobi_Kenya_Africa",
            "sunmccuRecordType": "STATION-HOURLY-MAINS-POWER-DATA",
            "sunmccuTxidKey": "1773819000-122947",
            "sunmccuData": "{\"Hourly Mains Power Status\": {\"0:00\": \"0\", \"1:00\": \"0\", \"2:00\": \"0\", \"3:00\": \"0\", \"4:00\": \"0\", \"5:00\": \"0\", \"6:00\": \"0\", \"7:00\": \"0\", \"8:00\": \"0\", \"9:00\": \"0\", \"10:00\": \"0\", \"11:00\": \"0\", \"12:00\": \"0\", \"13:00\": \"0\", \"14:00\": \"0\", \"15:00\": \"0\", \"16:00\": \"0\", \"17:00\": \"0\", \"18:00\": \"0\", \"19:00\": \"0\", \"20:00\": \"0\", \"21:00\": \"0\", \"22:00\": \"0\", \"23:00\": \"0\"}}",
            "sunmccuSource": "{\"type\": \"NAME\", \"address\": \"qis.xm.all.health\"}"
        },
        {
            "stationSerialNumber": "WMQISXM1V1-00917",
            "sunmccuTime": 1773817317936,
            "sunmccuDate": "2026-03-18T12:31:57Z",
            "location": "Shell_Lavington_Nairobi_Kenya",
            "zone": "Nairobi_Kenya_Africa",
            "sunmccuRecordType": "STATION-HOURLY-MAINS-POWER-DATA",
            "sunmccuTxidKey": "1773817317-936855",
            "sunmccuData": "{\"Hourly Mains Power Status\": {\"0:00\": \"0\", \"1:00\": \"0\", \"2:00\": \"0\", \"3:00\": \"0\", \"4:00\": \"0\", \"5:00\": \"0\", \"6:00\": \"0\", \"7:00\": \"0\", \"8:00\": \"0\", \"9:00\": \"0\", \"10:00\": \"0\", \"11:00\": \"0\", \"12:00\": \"0\", \"13:00\": \"0\", \"14:00\": \"0\", \"15:00\": \"0\", \"16:00\": \"0\", \"17:00\": \"0\", \"18:00\": \"0\", \"19:00\": \"0\", \"20:00\": \"0\", \"21:00\": \"0\", \"22:00\": \"0\", \"23:00\": \"0\"}}",
            "sunmccuSource": "{\"type\": \"NAME\", \"address\": \"qis.xm.all.health\"}"
        },
        {
            "stationSerialNumber": "WMQISXM1V1-00914",
            "sunmccuTime": 1773813703129,
            "sunmccuDate": "2026-03-18T11:31:43Z",
            "location": "Shell_Baraka_Waiyaki_Nairobi_Kenya",
            "zone": "Nairobi_Kenya_Africa",
            "sunmccuRecordType": "STATION-HOURLY-MAINS-POWER-DATA",
            "sunmccuTxidKey": "1773813703-129642",
            "sunmccuData": "{\"Hourly Mains Power Status\": {\"0:00\": \"0\", \"1:00\": \"0\", \"2:00\": \"0\", \"3:00\": \"0\", \"4:00\": \"0\", \"5:00\": \"0\", \"6:00\": \"0\", \"7:00\": \"0\", \"8:00\": \"0\", \"9:00\": \"0\", \"10:00\": \"0\", \"11:00\": \"0\", \"12:00\": \"0\", \"13:00\": \"0\", \"14:00\": \"0\", \"15:00\": \"0\", \"16:00\": \"0\", \"17:00\": \"0\", \"18:00\": \"0\", \"19:00\": \"0\", \"20:00\": \"0\", \"21:00\": \"0\", \"22:00\": \"0\", \"23:00\": \"0\"}}",
            "sunmccuSource": "{\"type\": \"NAME\", \"address\": \"qis.xm.all.health\"}"
        }
    ]
}